{
  "info": {
    "resource": "commonplayerinfo",
    "parameters": [
      {
        "PlayerID": 76003
      },
      {
        "LeagueID": null
      }
    ],
    "resultSets": [
      {
        "name": "CommonPlayerInfo",
        "headers": [
          "PERSON_ID",
          "FIRST_NAME",
          "LAST_NAME",
          "DISPLAY_FIRST_LAST",
          "DISPLAY_LAST_COMMA_FIRST",
          "DISPLAY_FI_LAST",
          "PLAYER_SLUG",
          "BIRTHDATE",
          "SCHOOL",
          "COUNTRY",
          "LAST_AFFILIATION",
          "HEIGHT",
          "WEIGHT",
          "SEASON_EXP",
          "JERSEY",
          "POSITION",
          "ROSTERSTATUS",
          "GAMES_PLAYED_CURRENT_SEASON_FLAG",
          "TEAM_ID",
          "TEAM_NAME",
          "TEAM_ABBREVIATION",
          "TEAM_CODE",
          "TEAM_CITY",
          "PLAYERCODE",
          "FROM_YEAR",
          "TO_YEAR",
          "DLEAGUE_FLAG",
          "NBA_FLAG",
          "GAMES_PLAYED_FLAG",
          "DRAFT_YEAR",
          "DRAFT_ROUND",
          "DRAFT_NUMBER",
          "GREATEST_75_FLAG"
        ],
        "rowSet": [
          [
            76003,
            "Kareem",
            "Abdul-Jabbar",
            "Kareem Abdul-Jabbar",
            "Abdul-Jabbar, Kareem",
            "K. Abdul-Jabbar",
            "kareem-abdul-jabbar",
            "1947-04-16T00:00:00",
            "UCLA",
            "USA",
            "UCLA/USA",
            "7-2",
            "225",
            20,
            "33",
            "Center",
            "Inactive",
            "N",
            1610612747,
            "Lakers",
            "LAL",
            "lakers",
            "Los Angeles",
            "HISTADD_kareem_abdul-jabbar",
            1969,
            1988,
            "N",
            "Y",
            "Y",
            "1969",
            "1",
            "1",
            "Y"
          ]
        ]
      },
      {
        "name": "PlayerHeadlineStats",
        "headers": [
          "PLAYER_ID",
          "PLAYER_NAME",
          "TimeFrame",
          "PTS",
          "AST",
          "REB",
          "ALL_STAR_APPEARANCES"
        ],
        "rowSet": [
          [76003, "Kareem Abdul-Jabbar", "career", 24.6, 3.6, 11.2, 18]
        ]
      },
      {
        "name": "AvailableSeasons",
        "headers": ["SEASON_ID"],
        "rowSet": [
          ["21969"],
          ["31969"],
          ["41969"],
          ["21970"],
          ["31970"],
          ["41970"],
          ["21971"],
          ["31971"],
          ["41971"],
          ["21972"],
          ["41972"],
          ["21973"],
          ["31973"],
          ["41973"],
          ["21974"],
          ["31974"],
          ["21975"],
          ["31975"],
          ["21976"],
          ["31976"],
          ["41976"],
          ["21977"],
          ["41977"],
          ["21978"],
          ["31978"],
          ["41978"],
          ["21979"],
          ["31979"],
          ["41979"],
          ["21980"],
          ["31980"],
          ["41980"],
          ["21981"],
          ["31981"],
          ["41981"],
          ["21982"],
          ["31982"],
          ["41982"],
          ["21983"],
          ["31983"],
          ["41983"],
          ["21984"],
          ["31984"],
          ["41984"],
          ["21985"],
          ["31985"],
          ["41985"],
          ["21986"],
          ["31986"],
          ["41986"],
          ["21987"],
          ["31987"],
          ["41987"],
          ["21988"],
          ["31988"],
          ["41988"]
        ]
      }
    ]
  },
  "awards": {
    "resource": "playerawards",
    "parameters": {
      "PlayerID": 76003
    },
    "resultSets": [
      {
        "name": "PlayerAwards",
        "headers": [
          "PERSON_ID",
          "FIRST_NAME",
          "LAST_NAME",
          "TEAM",
          "DESCRIPTION",
          "ALL_NBA_TEAM_NUMBER",
          "SEASON",
          "MONTH",
          "WEEK",
          "CONFERENCE",
          "TYPE",
          "SUBTYPE1",
          "SUBTYPE2",
          "SUBTYPE3"
        ],
        "rowSet": [
          [
            76003,
            "Kareem",
            "Abdul-Jabbar",
            "Milwaukee Bucks",
            "All-Defensive Team",
            "2",
            "1969-70",
            null,
            null,
            "1610612749",
            "Award",
            "Kia Motors",
            "KIADT",
            null
          ],
          [
            76003,
            "Kareem",
            "Abdul-Jabbar",
            "Milwaukee Bucks",
            "All-Defensive Team",
            "2",
            "1970-71",
            null,
            null,
            "1610612749",
            "Award",
            "Kia Motors",
            "KIADT",
            null
          ],
          [
            76003,
            "Kareem",
            "Abdul-Jabbar",
            "Milwaukee Bucks",
            "All-Defensive Team",
            "1",
            "1973-74",
            null,
            null,
            "1610612749",
            "Award",
            "Kia Motors",
            "KIADT",
            null
          ],
          [
            76003,
            "Kareem",
            "Abdul-Jabbar",
            "Milwaukee Bucks",
            "All-Defensive Team",
            "1",
            "1974-75",
            null,
            null,
            "1610612749",
            "Award",
            "Kia Motors",
            "KIADT",
            null
          ],
          [
            76003,
            "Kareem",
            "Abdul-Jabbar",
            "Los Angeles Lakers",
            "All-Defensive Team",
            "2",
            "1975-76",
            null,
            null,
            "1610612747",
            "Award",
            "Kia Motors",
            "KIADT",
            null
          ],
          [
            76003,
            "Kareem",
            "Abdul-Jabbar",
            "Los Angeles Lakers",
            "All-Defensive Team",
            "2",
            "1976-77",
            null,
            null,
            "1610612747",
            "Award",
            "Kia Motors",
            "KIADT",
            null
          ],
          [
            76003,
            "Kareem",
            "Abdul-Jabbar",
            "Los Angeles Lakers",
            "All-Defensive Team",
            "2",
            "1977-78",
            null,
            null,
            "1610612747",
            "Award",
            "Kia Motors",
            "KIADT",
            null
          ],
          [
            76003,
            "Kareem",
            "Abdul-Jabbar",
            "Los Angeles Lakers",
            "All-Defensive Team",
            "1",
            "1978-79",
            null,
            null,
            "1610612747",
            "Award",
            "Kia Motors",
            "KIADT",
            null
          ],
          [
            76003,
            "Kareem",
            "Abdul-Jabbar",
            "Los Angeles Lakers",
            "All-Defensive Team",
            "1",
            "1979-80",
            null,
            null,
            "1610612747",
            "Award",
            "Kia Motors",
            "KIADT",
            null
          ],
          [
            76003,
            "Kareem",
            "Abdul-Jabbar",
            "Los Angeles Lakers",
            "All-Defensive Team",
            "1",
            "1980-81",
            null,
            null,
            "1610612747",
            "Award",
            "Kia Motors",
            "KIADT",
            null
          ],
          [
            76003,
            "Kareem",
            "Abdul-Jabbar",
            "Los Angeles Lakers",
            "All-Defensive Team",
            "2",
            "1983-84",
            null,
            null,
            "1610612747",
            "Award",
            "Kia Motors",
            "KIADT",
            null
          ],
          [
            76003,
            "Kareem",
            "Abdul-Jabbar",
            "Milwaukee Bucks",
            "All-NBA",
            "2",
            "1969-70",
            null,
            null,
            "1610612749",
            "Award",
            "Kia Motors",
            "KIANT",
            null
          ],
          [
            76003,
            "Kareem",
            "Abdul-Jabbar",
            "Milwaukee Bucks",
            "All-NBA",
            "1",
            "1970-71",
            null,
            null,
            "1610612749",
            "Award",
            "Kia Motors",
            "KIANT",
            null
          ],
          [
            76003,
            "Kareem",
            "Abdul-Jabbar",
            "Milwaukee Bucks",
            "All-NBA",
            "1",
            "1971-72",
            null,
            null,
            "1610612749",
            "Award",
            "Kia Motors",
            "KIANT",
            null
          ],
          [
            76003,
            "Kareem",
            "Abdul-Jabbar",
            "Milwaukee Bucks",
            "All-NBA",
            "1",
            "1972-73",
            null,
            null,
            "1610612749",
            "Award",
            "Kia Motors",
            "KIANT",
            null
          ],
          [
            76003,
            "Kareem",
            "Abdul-Jabbar",
            "Milwaukee Bucks",
            "All-NBA",
            "1",
            "1973-74",
            null,
            null,
            "1610612749",
            "Award",
            "Kia Motors",
            "KIANT",
            null
          ],
          [
            76003,
            "Kareem",
            "Abdul-Jabbar",
            "Los Angeles Lakers",
            "All-NBA",
            "1",
            "1975-76",
            null,
            null,
            "1610612747",
            "Award",
            "Kia Motors",
            "KIANT",
            null
          ],
          [
            76003,
            "Kareem",
            "Abdul-Jabbar",
            "Los Angeles Lakers",
            "All-NBA",
            "1",
            "1976-77",
            null,
            null,
            "1610612747",
            "Award",
            "Kia Motors",
            "KIANT",
            null
          ],
          [
            76003,
            "Kareem",
            "Abdul-Jabbar",
            "Los Angeles Lakers",
            "All-NBA",
            "2",
            "1977-78",
            null,
            null,
            "1610612747",
            "Award",
            "Kia Motors",
            "KIANT",
            null
          ],
          [
            76003,
            "Kareem",
            "Abdul-Jabbar",
            "Los Angeles Lakers",
            "All-NBA",
            "2",
            "1978-79",
            null,
            null,
            "1610612747",
            "Award",
            "Kia Motors",
            "KIANT",
            null
          ],
          [
            76003,
            "Kareem",
            "Abdul-Jabbar",
            "Los Angeles Lakers",
            "All-NBA",
            "1",
            "1979-80",
            null,
            null,
            "1610612747",
            "Award",
            "Kia Motors",
            "KIANT",
            null
          ],
          [
            76003,
            "Kareem",
            "Abdul-Jabbar",
            "Los Angeles Lakers",
            "All-NBA",
            "1",
            "1980-81",
            null,
            null,
            "1610612747",
            "Award",
            "Kia Motors",
            "KIANT",
            null
          ],
          [
            76003,
            "Kareem",
            "Abdul-Jabbar",
            "Los Angeles Lakers",
            "All-NBA",
            "2",
            "1982-83",
            null,
            null,
            "1610612747",
            "Award",
            "Kia Motors",
            "KIANT",
            null
          ],
          [
            76003,
            "Kareem",
            "Abdul-Jabbar",
            "Los Angeles Lakers",
            "All-NBA",
            "1",
            "1983-84",
            null,
            null,
            "1610612747",
            "Award",
            "Kia Motors",
            "KIANT",
            null
          ],
          [
            76003,
            "Kareem",
            "Abdul-Jabbar",
            "Los Angeles Lakers",
            "All-NBA",
            "2",
            "1984-85",
            null,
            null,
            "1610612747",
            "Award",
            "Kia Motors",
            "KIANT",
            null
          ],
          [
            76003,
            "Kareem",
            "Abdul-Jabbar",
            "Los Angeles Lakers",
            "All-NBA",
            "1",
            "1985-86",
            null,
            null,
            "1610612747",
            "Award",
            "Kia Motors",
            "KIANT",
            null
          ],
          [
            76003,
            "Kareem",
            "Abdul-Jabbar",
            "Milwaukee Bucks",
            "All-Rookie Team",
            "1",
            "1969-70",
            null,
            null,
            "1610612749",
            "Award",
            "Kia Motors",
            "KIART",
            null
          ],
          [
            76003,
            "Kareem",
            "Abdul-Jabbar",
            null,
            "Hall of Fame Inductee",
            null,
            "1995",
            null,
            null,
            null,
            "Award",
            "Hall of Fame",
            null,
            null
          ],
          [
            76003,
            "Kareem",
            "Abdul-Jabbar",
            "Milwaukee Bucks",
            "NBA Finals Most Valuable Player",
            null,
            "1970-71",
            null,
            null,
            null,
            "Award",
            "Kia Motors",
            "KFMVP",
            null
          ],
          [
            76003,
            "Kareem",
            "Abdul-Jabbar",
            "Los Angeles Lakers",
            "NBA Finals Most Valuable Player",
            null,
            "1984-85",
            null,
            null,
            null,
            "Award",
            "Kia Motors",
            "KFMVP",
            null
          ],
          [
            76003,
            "Kareem",
            "Abdul-Jabbar",
            "Milwaukee Bucks",
            "NBA Most Valuable Player",
            null,
            "1970-71",
            null,
            null,
            null,
            "Award",
            "Kia Motors",
            "KIMVP",
            null
          ],
          [
            76003,
            "Kareem",
            "Abdul-Jabbar",
            "Milwaukee Bucks",
            "NBA Most Valuable Player",
            null,
            "1971-72",
            null,
            null,
            null,
            "Award",
            "Kia Motors",
            "KIMVP",
            null
          ],
          [
            76003,
            "Kareem",
            "Abdul-Jabbar",
            "Milwaukee Bucks",
            "NBA Most Valuable Player",
            null,
            "1973-74",
            null,
            null,
            null,
            "Award",
            "Kia Motors",
            "KIMVP",
            null
          ],
          [
            76003,
            "Kareem",
            "Abdul-Jabbar",
            "Los Angeles Lakers",
            "NBA Most Valuable Player",
            null,
            "1975-76",
            null,
            null,
            null,
            "Award",
            "Kia Motors",
            "KIMVP",
            null
          ],
          [
            76003,
            "Kareem",
            "Abdul-Jabbar",
            "Los Angeles Lakers",
            "NBA Most Valuable Player",
            null,
            "1976-77",
            null,
            null,
            null,
            "Award",
            "Kia Motors",
            "KIMVP",
            null
          ],
          [
            76003,
            "Kareem",
            "Abdul-Jabbar",
            "Los Angeles Lakers",
            "NBA Most Valuable Player",
            null,
            "1979-80",
            null,
            null,
            null,
            "Award",
            "Kia Motors",
            "KIMVP",
            null
          ],
          [
            76003,
            "Kareem",
            "Abdul-Jabbar",
            "Los Angeles Lakers",
            "NBA Player of the Month",
            null,
            "1979-80",
            "12/01/1979",
            null,
            null,
            "Award",
            "Kia Motors",
            "KIPMO",
            null
          ],
          [
            76003,
            "Kareem",
            "Abdul-Jabbar",
            "Los Angeles Lakers",
            "NBA Player of the Month",
            null,
            "1983-84",
            "03/01/1984",
            null,
            null,
            "Award",
            "Kia Motors",
            "KIPMO",
            null
          ],
          [
            76003,
            "Kareem",
            "Abdul-Jabbar",
            "Los Angeles Lakers",
            "NBA Player of the Week",
            null,
            "1979-80",
            null,
            "1979-12-09T00:00:00",
            null,
            "Award",
            "Kia Motors",
            "KIPWK",
            null
          ],
          [
            76003,
            "Kareem",
            "Abdul-Jabbar",
            "Los Angeles Lakers",
            "NBA Player of the Week",
            null,
            "1979-80",
            null,
            "1980-02-17T00:00:00",
            null,
            "Award",
            "Kia Motors",
            "KIPWK",
            null
          ],
          [
            76003,
            "Kareem",
            "Abdul-Jabbar",
            "Los Angeles Lakers",
            "NBA Player of the Week",
            null,
            "1980-81",
            null,
            "1980-12-21T00:00:00",
            null,
            "Award",
            "Kia Motors",
            "KIPWK",
            null
          ],
          [
            76003,
            "Kareem",
            "Abdul-Jabbar",
            "Los Angeles Lakers",
            "NBA Player of the Week",
            null,
            "1981-82",
            null,
            "1982-02-28T00:00:00",
            null,
            "Award",
            "Kia Motors",
            "KIPWK",
            null
          ],
          [
            76003,
            "Kareem",
            "Abdul-Jabbar",
            "Los Angeles Lakers",
            "NBA Player of the Week",
            null,
            "1983-84",
            null,
            "1984-02-12T00:00:00",
            null,
            "Award",
            "Kia Motors",
            "KIPWK",
            null
          ],
          [
            76003,
            "Kareem",
            "Abdul-Jabbar",
            "Los Angeles Lakers",
            "NBA Player of the Week",
            null,
            "1983-84",
            null,
            "1984-04-08T00:00:00",
            null,
            "Award",
            "Kia Motors",
            "KIPWK",
            null
          ],
          [
            76003,
            "Kareem",
            "Abdul-Jabbar",
            "Los Angeles Lakers",
            "NBA Player of the Week",
            null,
            "1984-85",
            null,
            "1985-03-24T00:00:00",
            null,
            "Award",
            "Kia Motors",
            "KIPWK",
            null
          ],
          [
            76003,
            "Kareem",
            "Abdul-Jabbar",
            "Milwaukee Bucks",
            "NBA Rookie of the Year",
            null,
            "1969-70",
            null,
            null,
            null,
            "Award",
            "Kia Motors",
            "KIROY",
            null
          ],
          [
            76003,
            "Kareem",
            "Abdul-Jabbar",
            "Milwaukee Bucks",
            "NBA Sporting News Most Valuable Player of the Year",
            null,
            "1970-71",
            null,
            null,
            null,
            "Award",
            "Sporting News",
            "SNMVP",
            null
          ],
          [
            76003,
            "Kareem",
            "Abdul-Jabbar",
            "Milwaukee Bucks",
            "NBA Sporting News Most Valuable Player of the Year",
            null,
            "1971-72",
            null,
            null,
            null,
            "Award",
            "Sporting News",
            "SNMVP",
            null
          ],
          [
            76003,
            "Kareem",
            "Abdul-Jabbar",
            "Milwaukee Bucks",
            "NBA Sporting News Most Valuable Player of the Year",
            null,
            "1973-74",
            null,
            null,
            null,
            "Award",
            "Sporting News",
            "SNMVP",
            null
          ],
          [
            76003,
            "Kareem",
            "Abdul-Jabbar",
            "Los Angeles Lakers",
            "NBA Sporting News Most Valuable Player of the Year",
            null,
            "1975-76",
            null,
            null,
            null,
            "Award",
            "Sporting News",
            "SNMVP",
            null
          ],
          [
            76003,
            "Kareem",
            "Abdul-Jabbar",
            "Los Angeles Lakers",
            "NBA Sporting News Most Valuable Player of the Year",
            null,
            "1976-77",
            null,
            null,
            null,
            "Award",
            "Sporting News",
            "SNMVP",
            null
          ],
          [
            76003,
            "Kareem",
            "Abdul-Jabbar",
            "Los Angeles Lakers",
            "NBA Sporting News Most Valuable Player of the Year",
            null,
            "1979-80",
            null,
            null,
            null,
            "Award",
            "Sporting News",
            "SNMVP",
            null
          ],
          [
            76003,
            "Kareem",
            "Abdul-Jabbar",
            "Milwaukee Bucks",
            "NBA Sporting News Rookie of the Year",
            null,
            "1969-70",
            null,
            null,
            null,
            "Award",
            "Sporting News",
            "SNROY",
            null
          ],
          [
            76003,
            "Kareem",
            "Abdul-Jabbar",
            null,
            "NBA All-Star",
            null,
            "1969-70",
            null,
            null,
            null,
            "Award",
            "All-Star",
            null,
            null
          ],
          [
            76003,
            "Kareem",
            "Abdul-Jabbar",
            null,
            "NBA All-Star",
            null,
            "1970-71",
            null,
            null,
            null,
            "Award",
            "All-Star",
            null,
            null
          ],
          [
            76003,
            "Kareem",
            "Abdul-Jabbar",
            null,
            "NBA All-Star",
            null,
            "1971-72",
            null,
            null,
            null,
            "Award",
            "All-Star",
            null,
            null
          ],
          [
            76003,
            "Kareem",
            "Abdul-Jabbar",
            null,
            "NBA All-Star",
            null,
            "1973-74",
            null,
            null,
            null,
            "Award",
            "All-Star",
            null,
            null
          ],
          [
            76003,
            "Kareem",
            "Abdul-Jabbar",
            null,
            "NBA All-Star",
            null,
            "1974-75",
            null,
            null,
            null,
            "Award",
            "All-Star",
            null,
            null
          ],
          [
            76003,
            "Kareem",
            "Abdul-Jabbar",
            null,
            "NBA All-Star",
            null,
            "1975-76",
            null,
            null,
            null,
            "Award",
            "All-Star",
            null,
            null
          ],
          [
            76003,
            "Kareem",
            "Abdul-Jabbar",
            null,
            "NBA All-Star",
            null,
            "1976-77",
            null,
            null,
            null,
            "Award",
            "All-Star",
            null,
            null
          ],
          [
            76003,
            "Kareem",
            "Abdul-Jabbar",
            null,
            "NBA All-Star",
            null,
            "1978-79",
            null,
            null,
            null,
            "Award",
            "All-Star",
            null,
            null
          ],
          [
            76003,
            "Kareem",
            "Abdul-Jabbar",
            null,
            "NBA All-Star",
            null,
            "1979-80",
            null,
            null,
            null,
            "Award",
            "All-Star",
            null,
            null
          ],
          [
            76003,
            "Kareem",
            "Abdul-Jabbar",
            null,
            "NBA All-Star",
            null,
            "1980-81",
            null,
            null,
            null,
            "Award",
            "All-Star",
            null,
            null
          ],
          [
            76003,
            "Kareem",
            "Abdul-Jabbar",
            null,
            "NBA All-Star",
            null,
            "1981-82",
            null,
            null,
            null,
            "Award",
            "All-Star",
            null,
            null
          ],
          [
            76003,
            "Kareem",
            "Abdul-Jabbar",
            null,
            "NBA All-Star",
            null,
            "1982-83",
            null,
            null,
            null,
            "Award",
            "All-Star",
            null,
            null
          ],
          [
            76003,
            "Kareem",
            "Abdul-Jabbar",
            null,
            "NBA All-Star",
            null,
            "1983-84",
            null,
            null,
            null,
            "Award",
            "All-Star",
            null,
            null
          ],
          [
            76003,
            "Kareem",
            "Abdul-Jabbar",
            null,
            "NBA All-Star",
            null,
            "1984-85",
            null,
            null,
            null,
            "Award",
            "All-Star",
            null,
            null
          ],
          [
            76003,
            "Kareem",
            "Abdul-Jabbar",
            null,
            "NBA All-Star",
            null,
            "1985-86",
            null,
            null,
            null,
            "Award",
            "All-Star",
            null,
            null
          ],
          [
            76003,
            "Kareem",
            "Abdul-Jabbar",
            null,
            "NBA All-Star",
            null,
            "1986-87",
            null,
            null,
            null,
            "Award",
            "All-Star",
            null,
            null
          ],
          [
            76003,
            "Kareem",
            "Abdul-Jabbar",
            null,
            "NBA All-Star",
            null,
            "1987-88",
            null,
            null,
            null,
            "Award",
            "All-Star",
            null,
            null
          ],
          [
            76003,
            "Kareem",
            "Abdul-Jabbar",
            null,
            "NBA All-Star",
            null,
            "1988-89",
            null,
            null,
            null,
            "Award",
            "All-Star",
            null,
            null
          ],
          [
            76003,
            "Kareem",
            "Abdul-Jabbar",
            null,
            "NBA All-Star",
            null,
            "1972-73",
            null,
            null,
            null,
            "Award",
            "All-Star",
            null,
            null
          ],
          [
            76003,
            "Kareem",
            "Abdul-Jabbar",
            "Los Angeles Lakers",
            "NBA Champion",
            "",
            "1979-80",
            null,
            null,
            "",
            "Award",
            "Champion",
            "",
            ""
          ],
          [
            76003,
            "Kareem",
            "Abdul-Jabbar",
            "Los Angeles Lakers",
            "NBA Champion",
            "",
            "1981-82",
            null,
            null,
            "",
            "Award",
            "Champion",
            "",
            ""
          ],
          [
            76003,
            "Kareem",
            "Abdul-Jabbar",
            "Los Angeles Lakers",
            "NBA Champion",
            "",
            "1984-85",
            null,
            null,
            "",
            "Award",
            "Champion",
            "",
            ""
          ],
          [
            76003,
            "Kareem",
            "Abdul-Jabbar",
            "Los Angeles Lakers",
            "NBA Champion",
            "",
            "1986-87",
            null,
            null,
            "",
            "Award",
            "Champion",
            "",
            ""
          ],
          [
            76003,
            "Kareem",
            "Abdul-Jabbar",
            "Los Angeles Lakers",
            "NBA Champion",
            "",
            "1987-88",
            null,
            null,
            "",
            "Award",
            "Champion",
            "",
            ""
          ],
          [
            76003,
            "Kareem",
            "Abdul-Jabbar",
            "Milwaukee Bucks",
            "NBA Champion",
            "",
            "1970-71",
            null,
            null,
            "",
            "Award",
            "Champion",
            "",
            ""
          ]
        ]
      }
    ]
  },
  "stats": {
    "headers": [
      "PLAYER_ID",
      "LEAGUE_ID",
      "Team_ID",
      "GP",
      "GS",
      "MIN",
      "FGM",
      "FGA",
      "FG_PCT",
      "FG3M",
      "FG3A",
      "FG3_PCT",
      "FTM",
      "FTA",
      "FT_PCT",
      "OREB",
      "DREB",
      "REB",
      "AST",
      "STL",
      "BLK",
      "TOV",
      "PF",
      "PTS"
    ],
    "data": [
      [
        76003,
        "00",
        0,
        1560,
        1476,
        36.8,
        10.2,
        18.1,
        0.559,
        0.0,
        null,
        null,
        4.3,
        6.0,
        0.721,
        2.4,
        7.6,
        11.2,
        3.6,
        0.9,
        2.6,
        2.7,
        3.0,
        24.6
      ]
    ]
  }
}
